hv/__init__.py
hv/adb.py
hv/cmds.py
hv/settings.py
hv/apks/app-debug-androidTest.apk
hv/apks/app-debug.apk
share_hv-0.0.4.dist-info/LICENSE
share_hv-0.0.4.dist-info/METADATA
share_hv-0.0.4.dist-info/WHEEL
share_hv-0.0.4.dist-info/entry_points.txt
share_hv-0.0.4.dist-info/top_level.txt
share_hv-0.0.4.dist-info/RECORD
