Metadata-Version: 2.1
Name: share-hv
Version: 0.0.4
Summary: Share simple hierarchy-view like screenshots of your Android app
Home-page: https://github.com/kbsriram/share-hv-python-client
Author: KB Sriram
Author-email: kbsriram@gmail.com
License: UNKNOWN
Platform: UNKNOWN
Classifier: Programming Language :: Python :: 3
Classifier: License :: OSI Approved :: Apache Software License
Requires-Python: >=3.6
Requires-Dist: Click (>=7.1.2)
Requires-Dist: requests (>=2.24)
Provides-Extra: dev
Requires-Dist: check-manifest ; extra == 'dev'
Requires-Dist: pytest (>=3.6) ; extra == 'dev'
Requires-Dist: twine ; extra == 'dev'
